vpy/__init__.py
vpy/fileio.py
vpy/types.py
vpy_module-0.0.1.dist-info/METADATA
vpy_module-0.0.1.dist-info/WHEEL
vpy_module-0.0.1.dist-info/top_level.txt
vpy_module-0.0.1.dist-info/RECORD
