Metadata-Version: 2.1
Name: vpy-module
Version: 0.0.1
Summary: Python API for https://github.com/HuangPatrick16777216/video_editor
Home-page: https://github.com/HuangPatrick16777216/video_editor
Author: Patrick Huang
Author-email: huangpatrick16777216@gmail.com
License: UNKNOWN
Platform: UNKNOWN
Classifier: Programming Language :: Python :: 3
Classifier: License :: OSI Approved :: GNU General Public License v2 or later (GPLv2+)
Classifier: Operating System :: OS Independent
